noos_jupyter_authenticator/__init__.py
noos_jupyter_authenticator/authenticators.py
noos_jupyter_authenticator/clients.py
noos_jupyter_authenticator/handlers.py
noos_jupyter_authenticator-0.2.0.dist-info/LICENSE
noos_jupyter_authenticator-0.2.0.dist-info/METADATA
noos_jupyter_authenticator-0.2.0.dist-info/WHEEL
noos_jupyter_authenticator-0.2.0.dist-info/RECORD
