Metadata-Version: 2.1
Name: noos-jupyter-authenticator
Version: 0.2.0
Summary: JupyterHub authenticator for the Noos platform.
Home-page: https://github.com/noosenergy/noos-jupyter-authenticator
License: MIT
Author: Noos Energy
Author-email: contact@noos.energy
Requires-Python: >=3.12,<4.0
Classifier: Development Status :: 5 - Production/Stable
Classifier: Intended Audience :: Developers
Classifier: License :: OSI Approved :: MIT License
Classifier: Operating System :: OS Independent
Classifier: Programming Language :: Python :: 3
Classifier: Programming Language :: Python :: 3.12
Classifier: Typing :: Typed
Requires-Dist: jupyterhub (>=3.0.0,<4.0.0)
Requires-Dist: noos-pyk
Requires-Dist: tornado
Requires-Dist: traitlets
